Changelog.md
LICENSE
MANIFEST.in
README.md
requirements.txt
setup.cfg
setup.py
supportedsites.md
VIP_yt/YoutubeDL.py
VIP_yt/__init__.py
VIP_yt/__main__.py
VIP_yt/aes.py
VIP_yt/cache.py
VIP_yt/cookies.py
VIP_yt/dependencies.py
VIP_yt/jsinterp.py
VIP_yt/minicurses.py
VIP_yt/options.py
VIP_yt/socks.py
VIP_yt/update.py
VIP_yt/utils.py
VIP_yt/version.py
VIP_yt/webvtt.py
VIP_yt.egg-info/PKG-INFO
VIP_yt.egg-info/SOURCES.txt
VIP_yt.egg-info/dependency_links.txt
VIP_yt.egg-info/entry_points.txt
VIP_yt.egg-info/requires.txt
VIP_yt.egg-info/top_level.txt
VIP_yt/compat/__init__.py
VIP_yt/compat/_deprecated.py
VIP_yt/compat/_legacy.py
VIP_yt/compat/compat_utils.py
VIP_yt/compat/functools.py
VIP_yt/compat/imghdr.py
VIP_yt/downloader/__init__.py
VIP_yt/downloader/common.py
VIP_yt/downloader/dash.py
VIP_yt/downloader/external.py
VIP_yt/downloader/f4m.py
VIP_yt/downloader/fc2.py
VIP_yt/downloader/fragment.py
VIP_yt/downloader/hls.py
VIP_yt/downloader/http.py
VIP_yt/downloader/ism.py
VIP_yt/downloader/mhtml.py
VIP_yt/downloader/niconico.py
VIP_yt/downloader/rtmp.py
VIP_yt/downloader/rtsp.py
VIP_yt/downloader/websocket.py
VIP_yt/downloader/youtube_live_chat.py
VIP_yt/extractor/__init__.py
VIP_yt/extractor/_extractors.py
VIP_yt/extractor/abc.py
VIP_yt/extractor/abcnews.py
VIP_yt/extractor/abcotvs.py
VIP_yt/extractor/abematv.py
VIP_yt/extractor/academicearth.py
VIP_yt/extractor/acast.py
VIP_yt/extractor/acfun.py
VIP_yt/extractor/adn.py
VIP_yt/extractor/adobeconnect.py
VIP_yt/extractor/adobepass.py
VIP_yt/extractor/adobetv.py
VIP_yt/extractor/adultswim.py
VIP_yt/extractor/aenetworks.py
VIP_yt/extractor/afreecatv.py
VIP_yt/extractor/airmozilla.py
VIP_yt/extractor/aliexpress.py
VIP_yt/extractor/aljazeera.py
VIP_yt/extractor/allocine.py
VIP_yt/extractor/alphaporno.py
VIP_yt/extractor/alsace20tv.py
VIP_yt/extractor/alura.py
VIP_yt/extractor/amara.py
VIP_yt/extractor/amazon.py
VIP_yt/extractor/amcnetworks.py
VIP_yt/extractor/americastestkitchen.py
VIP_yt/extractor/amp.py
VIP_yt/extractor/animeondemand.py
VIP_yt/extractor/ant1newsgr.py
VIP_yt/extractor/anvato.py
VIP_yt/extractor/aol.py
VIP_yt/extractor/apa.py
VIP_yt/extractor/aparat.py
VIP_yt/extractor/appleconnect.py
