Metadata-Version: 2.1
Name: VIP-yt
Version: 2022.7.26
Summary: A youtube-dl fork with additional features and patches
Home-page: https://github.com/VIP-yt/VIP-yt
Maintainer: Abdo-Asil
Maintainer-email: pukkandan.ytdlp@gmail.com
License: UNKNOWN
Project-URL: Documentation, https://github.com/VIP-yt/VIP-yt#readme
Project-URL: Source, https://github.com/VIP-yt/VIP-yt
Project-URL: Tracker, https://github.com/VIP-yt/VIP-yt/issues
Project-URL: Funding, https://github.com/VIP-yt/VIP-yt/blob/master/Collaborators.md#collaborators
Platform: UNKNOWN
Classifier: Topic :: Multimedia :: Video
Classifier: Development Status :: 5 - Production/Stable
Classifier: Environment :: Console
Classifier: Programming Language :: Python
Classifier: Programming Language :: Python :: 3.7
Classifier: Programming Language :: Python :: 3.8
Classifier: Programming Language :: Python :: 3.9
Classifier: Programming Language :: Python :: 3.10
Classifier: Programming Language :: Python :: 3.11
Classifier: Programming Language :: Python :: Implementation
Classifier: Programming Language :: Python :: Implementation :: CPython
Classifier: Programming Language :: Python :: Implementation :: PyPy
Classifier: License :: Public Domain
Classifier: Operating System :: OS Independent
Requires-Python: >=3.7
License-File: LICENSE
